Workbook

Sheet 折现数据源
A1: 折现数据源 (Discount Data Source) — 收益率曲线 + 折现因子 + 账户现金流
A2: 🟢 绿区 = 可编辑输入 (收益率/现金流) | 🟣 紫区 = 自动计算 (折现因子) | 修改此处，下游所有 sheet 自动联动
A3: 期限 | B3: 年数 (t) | C3: 利率 r_t (%) | D3: 折现因子 DF_t = 1/(1+r/100)^t | E3: 000000 1.1. 对公一般贷款 (资产) | F3: 000000 1.2. 个人贷款 (资产) | G3: 000000 1.3. 信用卡贷款 (资产) | H3: 000000 1.4. 票据贴现 (资产) | I3: 000000 1.5. 非银贷款 (资产) | J3: 010100 2.1.1 金市自营债券 (资产) | K3: 010200 2.1.2 司库债券 (资产) | L3: 000000 2.2. 结构化融资 (资产) | M3: 000000 2.3. 同业资产（不含 (资产) | N3: 000000 2.4. 存款准备金 (资产) | O3: 000000 3.1. FVTPL类资 (资产) | P3: 000000 3.2. 其他非生息资产 (资产) | Q3: 000000 1. 外币贷款 (资产) | R3: 000000 2.1. 外币债券 (资产) | S3: 000000 2.2. 同业资产 (资产) | T3: 000000 3. 外币非生息资产 (资产) | U3: 010100 1.1.1 对公活期存款 (负债) | V3: 010200 1.1.2 对公定期存款 (负债) | W3: 020100 1.2.1 零售活期存款 (负债) | X3: 020200 1.2.2 零售定期存款 (负债) | Y3: 000000 2. 人民币市场化负债 (负债) | Z3: 000000 1. 外币存款 (负债) | AA3: 000000 2. 外币市场化负债 (负债) | AB3: 000000 所有者权益 (权益)
A4: 1M | B4: 0.083333 | C4: 1.27 | D4: =1/(1+C4/100)^B4 | E4: 1080.2713 | F4: 771.6224 | G4: 211.645 | H4: 141.0967 | I4: 220.4635 | J4: 661.3906 | K4: 440.9271 | L4: 220.4635 | M4: 308.649 | N4: 132.2781 | O4: 132.2781 | P4: 88.1854 | Q4: 176.3708 | R4: 88.1854 | S4: 44.0927 | T4: 44.0927 | U4: 13000 | V4: 3883.7768 | W4: 6000 | X4: 3530.7061 | Y4: 2118.4237 | Z4: 706.1412 | AA4: 353.0706 | AB4: 0
A5: 2M | B5: 0.166667 | C5: 1.27 | D5: =1/(1+C5/100)^B5 | E5: 1080.2713 | F5: 771.6224 | G5: 211.645 | H5: 141.0967 | I5: 220.4635 | J5: 661.3906 | K5: 440.9271 | L5: 220.4635 | M5: 308.649 | N5: 132.2781 | O5: 132.2781 | P5: 88.1854 | Q5: 176.3708 | R5: 88.1854 | S5: 44.0927 | T5: 44.0927 | U5: 7800 | V5: 3883.7768 | W5: 3600 | X5: 3530.7061 | Y5: 2118.4237 | Z5: 706.1412 | AA5: 353.0706 | AB5: 0
A6: 3M | B6: 0.25 | C6: 1.27 | D6: =1/(1+C6/100)^B6 | E6: 1080.2713 | F6: 771.6224 | G6: 211.645 | H6: 141.0967 | I6: 220.4635 | J6: 661.3906 | K6: 440.9271 | L6: 220.4635 | M6: 308.649 | N6: 132.2781 | O6: 132.2781 | P6: 88.1854 | Q6: 176.3708 | R6: 88.1854 | S6: 44.0927 | T6: 44.0927 | U6: 5200 | V6: 2587.7175 | W6: 2400 | X6: 2352.4705 | Y6: 1411.4823 | Z6: 470.4941 | AA6: 235.247 | AB6: 0
A7: 4M | B7: 0.333333 | C7: 1.28 | D7: =1/(1+C7/100)^B7 | E7: 1080.2713 | F7: 771.6224 | G7: 211.645 | H7: 141.0967 | I7: 220.4635 | J7: 661.3906 | K7: 440.9271 | L7: 220.4635 | M7: 308.649 | N7: 132.2781 | O7: 132.2781 | P7: 88.1854 | Q7: 176.3708 | R7: 88.1854 | S7: 44.0927 | T7: 44.0927 | U7: 0 | V7: 1293.8588 | W7: 0 | X7: 1176.2352 | Y7: 705.7411 | Z7: 235.247 | AA7: 117.6235 | AB7: 0
A8: 5M | B8: 0.416667 | C8: 1.29 | D8: =1/(1+C8/100)^B8 | E8: 1080.2713 | F8: 771.6224 | G8: 211.645 | H8: 141.0967 | I8: 220.4635 | J8: 661.3906 | K8: 440.9271 | L8: 220.4635 | M8: 308.649 | N8: 132.2781 | O8: 132.2781 | P8: 88.1854 | Q8: 176.3708 | R8: 88.1854 | S8: 44.0927 | T8: 44.0927 | U8: 0 | V8: 1293.8588 | W8: 0 | X8: 1176.2352 | Y8: 705.7411 | Z8: 235.247 | AA8: 117.6235 | AB8: 0
A9: 6M | B9: 0.5 | C9: 1.3 | D9: =1/(1+C9/100)^B9 | E9: 1080.2713 | F9: 771.6224 | G9: 211.645 | H9: 141.0967 | I9: 220.4635 | J9: 661.3906 | K9: 440.9271 | L9: 220.4635 | M9: 308.649 | N9: 132.2781 | O9: 132.2781 | P9: 88.1854 | Q9: 176.3708 | R9: 88.1854 | S9: 44.0927 | T9: 44.0927 | U9: 0 | V9: 1293.8588 | W9: 0 | X9: 1176.2352 | Y9: 705.7411 | Z9: 235.247 | AA9: 117.6235 | AB9: 0
A10: 7M | B10: 0.583333 | C10: 1.31 | D10: =1/(1+C10/100)^B10 | E10: 1080.2713 | F10: 771.6224 | G10: 211.645 | H10: 141.0967 | I10: 220.4635 | J10: 661.3906 | K10: 440.9271 | L10: 220.4635 | M10: 308.649 | N10: 132.2781 | O10: 132.2781 | P10: 88.1854 | Q10: 176.3708 | R10: 88.1854 | S10: 44.0927 | T10: 44.0927 | U10: 0 | V10: 1293.8588 | W10: 0 | X10: 1176.2352 | Y10: 705.7411 | Z10: 235.247 | AA10: 117.6235 | AB10: 0
A11: 8M | B11: 0.666667 | C11: 1.315 | D11: =1/(1+C11/100)^B11 | E11: 1080.2713 | F11: 771.6224 | G11: 211.645 | H11: 141.0967 | I11: 220.4635 | J11: 661.3906 | K11: 440.9271 | L11: 220.4635 | M11: 308.649 | N11: 132.2781 | O11: 132.2781 | P11: 88.1854 | Q11: 176.3708 | R11: 88.1854 | S11: 44.0927 | T11: 44.0927 | U11: 0 | V11: 1293.8588 | W11: 0 | X11: 1176.2352 | Y11: 705.7411 | Z11: 235.247 | AA11: 117.6235 | AB11: 0
A12: 9M | B12: 0.75 | C12: 1.32 | D12: =1/(1+C12/100)^B12 | E12: 1080.2713 | F12: 771.6224 | G12: 211.645 | H12: 141.0967 | I12: 220.4635 | J12: 661.3906 | K12: 440.9271 | L12: 220.4635 | M12: 308.649 | N12: 132.2781 | O12: 132.2781 | P12: 88.1854 | Q12: 176.3708 | R12: 88.1854 | S12: 44.0927 | T12: 44.0927 | U12: 0 | V12: 1293.8588 | W12: 0 | X12: 1176.2352 | Y12: 705.7411 | Z12: 235.247 | AA12: 117.6235 | AB12: 0
A13: 10M | B13: 0.833333 | C13: 1.328 | D13: =1/(1+C13/100)^B13 | E13: 1080.2713 | F13: 771.6224 | G13: 211.645 | H13: 141.0967 | I13: 220.4635 | J13: 661.3906 | K13: 440.9271 | L13: 220.4635 | M13: 308.649 | N13: 132.2781 | O13: 132.2781 | P13: 88.1854 | Q13: 176.3708 | R13: 88.1854 | S13: 44.0927 | T13: 44.0927 | U13: 0 | V13: 1293.8588 | W13: 0 | X13: 1176.2352 | Y13: 705.7411 | Z13: 235.247 | AA13: 117.6235 | AB13: 0
A14: 11M | B14: 0.916667 | C14: 1.333 | D14: =1/(1+C14/100)^B14 | E14: 1080.2713 | F14: 771.6224 | G14: 211.645 | H14: 141.0967 | I14: 220.4635 | J14: 661.3906 | K14: 440.9271 | L14: 220.4635 | M14: 308.649 | N14: 132.2781 | O14: 132.2781 | P14: 88.1854 | Q14: 176.3708 | R14: 88.1854 | S14: 44.0927 | T14: 44.0927 | U14: 0 | V14: 1293.8588 | W14: 0 | X14: 1176.2352 | Y14: 705.7411 | Z14: 235.247 | AA14: 117.6235 | AB14: 0
A15: 12M | B15: 1 | C15: 1.3372 | D15: =1/(1+C15/100)^B15 | E15: 1080.2713 | F15: 771.6224 | G15: 211.645 | H15: 141.0967 | I15: 220.4635 | J15: 661.3906 | K15: 440.9271 | L15: 220.4635 | M15: 308.649 | N15: 132.2781 | O15: 132.2781 | P15: 88.1854 | Q15: 176.3708 | R15: 88.1854 | S15: 44.0927 | T15: 44.0927 | U15: 0 | V15: 1293.8588 | W15: 0 | X15: 1176.2352 | Y15: 705.7411 | Z15: 235.247 | AA15: 117.6235 | AB15: 0
... A67: 30Y | B67: 30 | C67: 2.2674 | D67: =1/(1+C67/100)^B67 | E67: 1440.3618 | F67: 1028.8298 | G67: 282.1933 | H67: 188.1289 | I67: 293.9514 | J67: 881.8542 | K67: 587.9028 | L67: 293.9514 | M67: 411.5319 | N67: 176.3708 | O67: 176.3708 | P67: 117.5806 | Q67: 235.1611 | R67: 117.5806 | S67: 58.7903 | T67: 58.7903 | U67: 0 | V67: 0 | W67: 0 | X67: 0 | Y67: 0 | Z67: 0 | AA67: 0 | AB67: 0
A69: 【数据来源】prcp_basic_20251231_v5.xlsx → 基础数据 sheet
A70: · 收益率曲线: B48-B111 = 64 段 (中债登 2025-12-31 + 线性插值)
A71: · 现金流: C76-C139 = 剩余·1M-60M (60 段) + 剩余·10Y/15Y/20Y/30Y (4 段)
A72: · 账户范围: 24 个末级账户 (is_leaf=1), 已剔除汇总行避免重复计算
A74: 【单位说明】
A75: · 利率列单位 = % (如 1.27 表示 1.27%)
A76: · 现金流列单位 = 亿元
A77: · 折现因子 = 1/(1 + 利率/100)^年数, 无量纲
A79: 【联动关系】
A80: · 修改 C 列 (利率) → D 列折现因子重算 → 麦考林久期计算表 / 久期缺口 / 期限分布 全部自动更新
A81: · 修改 E 列及以后 (现金流) → 同上

Sheet 麦考林久期计算表
A1: 麦考林久期计量表 (Macaulay Duration) — 中信银行 2025-12-31
A2: D_mac = Σ(t × PV_t) / Σ(PV_t) | D_mod = D_mac / (1 + y_avg) | 所有数值均由「折现数据源」sheet 公式计算，联动更新
A4: 账户编码 | B4: 账户名称 | C4: 大类 | D4: 当前余额 (亿元) | E4: PV 合计 (亿元) | F4: Σ t×PV (亿元·年) | G4: 麦考林久期 (年) | H4: 修正久期 (年) | I4: 加权平均收益率 (%) | J4: PV 占比 (%)
A5: S01010101000000 | B5: 1.1. 对公一般贷款 | C5: 资产 | D5: 24500 | E5: =SUMPRODUCT(折现数据源!E$4:E$67,折现数据源!$D$4:$D$67) | F5: =SUMPRODUCT(折现数据源!E$4:E$67,折现数据源!$D$4:$D$67,折现数据源!$B$4:$B$67) | G5: =IF(E5=0,0,F5/E5) | H5: =IF(I5=0,G5,G5/(1+I5)) | I5: =IF(E5=0,0,SUMPRODUCT(折现数据源!E$4:E$67,折现数据源!$C$4:$C$67/100,折现数据源!$D$4:$D$67)/E5) | J5: =IF(SUM($E$5:$E$28)=0,0,E5/SUM($E$5:$E$28))
A6: S01010102000000 | B6: 1.2. 个人贷款 | C6: 资产 | D6: 17500 | E6: =SUMPRODUCT(折现数据源!F$4:F$67,折现数据源!$D$4:$D$67) | F6: =SUMPRODUCT(折现数据源!F$4:F$67,折现数据源!$D$4:$D$67,折现数据源!$B$4:$B$67) | G6: =IF(E6=0,0,F6/E6) | H6: =IF(I6=0,G6,G6/(1+I6)) | I6: =IF(E6=0,0,SUMPRODUCT(折现数据源!F$4:F$67,折现数据源!$C$4:$C$67/100,折现数据源!$D$4:$D$67)/E6) | J6: =IF(SUM($E$5:$E$28)=0,0,E6/SUM($E$5:$E$28))
A7: S01010103000000 | B7: 1.3. 信用卡贷款 | C7: 资产 | D7: 4800 | E7: =SUMPRODUCT(折现数据源!G$4:G$67,折现数据源!$D$4:$D$67) | F7: =SUMPRODUCT(折现数据源!G$4:G$67,折现数据源!$D$4:$D$67,折现数据源!$B$4:$B$67) | G7: =IF(E7=0,0,F7/E7) | H7: =IF(I7=0,G7,G7/(1+I7)) | I7: =IF(E7=0,0,SUMPRODUCT(折现数据源!G$4:G$67,折现数据源!$C$4:$C$67/100,折现数据源!$D$4:$D$67)/E7) | J7: =IF(SUM($E$5:$E$28)=0,0,E7/SUM($E$5:$E$28))
A8: S01010104000000 | B8: 1.4. 票据贴现 | C8: 资产 | D8: 3200 | E8: =SUMPRODUCT(折现数据源!H$4:H$67,折现数据源!$D$4:$D$67) | F8: =SUMPRODUCT(折现数据源!H$4:H$67,折现数据源!$D$4:$D$67,折现数据源!$B$4:$B$67) | G8: =IF(E8=0,0,F8/E8) | H8: =IF(I8=0,G8,G8/(1+I8)) | I8: =IF(E8=0,0,SUMPRODUCT(折现数据源!H$4:H$67,折现数据源!$C$4:$C$67/100,折现数据源!$D$4:$D$67)/E8) | J8: =IF(SUM($E$5:$E$28)=0,0,E8/SUM($E$5:$E$28))
A9: S01010105000000 | B9: 1.5. 非银贷款 | C9: 资产 | D9: 5000 | E9: =SUMPRODUCT(折现数据源!I$4:I$67,折现数据源!$D$4:$D$67) | F9: =SUMPRODUCT(折现数据源!I$4:I$67,折现数据源!$D$4:$D$67,折现数据源!$B$4:$B$67) | G9: =IF(E9=0,0,F9/E9) | H9: =IF(I9=0,G9,G9/(1+I9)) | I9: =IF(E9=0,0,SUMPRODUCT(折现数据源!I$4:I$67,折现数据源!$C$4:$C$67/100,折现数据源!$D$4:$D$67)/E9) | J9: =IF(SUM($E$5:$E$28)=0,0,E9/SUM($E$5:$E$28))
A10: S010102010100 | B10: 2.1.1 金市自营债券 | C10: 资产 | D10: 15000 | E10: =SUMPRODUCT(折现数据源!J$4:J$67,折现数据源!$D$4:$D$67) | F10: =SUMPRODUCT(折现数据源!J$4:J$67,折现数据源!$D$4:$D$67,折现数据源!$B$4:$B$67) | G10: =IF(E10=0,0,F10/E10) | H10: =IF(I10=0,G10,G10/(1+I10)) | I10: =IF(E10=0,0,SUMPRODUCT(折现数据源!J$4:J$67,折现数据源!$C$4:$C$67/100,折现数据源!$D$4:$D$67)/E10) | J10: =IF(SUM($E$5:$E$28)=0,0,E10/SUM($E$5:$E$28))
A11: S010102010200 | B11: 2.1.2 司库债券 | C11: 资产 | D11: 10000 | E11: =SUMPRODUCT(折现数据源!K$4:K$67,折现数据源!$D$4:$D$67) | F11: =SUMPRODUCT(折现数据源!K$4:K$67,折现数据源!$D$4:$D$67,折现数据源!$B$4:$B$67) | G11: =IF(E11=0,0,F11/E11) | H11: =IF(I11=0,G11,G11/(1+I11)) | I11: =IF(E11=0,0,SUMPRODUCT(折现数据源!K$4:K$67,折现数据源!$C$4:$C$67/100,折现数据源!$D$4:$D$67)/E11) | J11: =IF(SUM($E$5:$E$28)=0,0,E11/SUM($E$5:$E$28))
A12: S01010202000000 | B12: 2.2. 结构化融资 | C12: 资产 | D12: 5000 | E12: =SUMPRODUCT(折现数据源!L$4:L$67,折现数据源!$D$4:$D$67) | F12: =SUMPRODUCT(折现数据源!L$4:L$67,折现数据源!$D$4:$D$67,折现数据源!$B$4:$B$67) | G12: =IF(E12=0,0,F12/E12) | H12: =IF(I12=0,G12,G12/(1+I12)) | I12: =IF(E12=0,0,SUMPRODUCT(折现数据源!L$4:L$67,折现数据源!$C$4:$C$67/100,折现数据源!$D$4:$D$67)/E12) | J12: =IF(SUM($E$5:$E$28)=0,0,E12/SUM($E$5:$E$28))
A13: S01010203000000 | B13: 2.3. 同业资产（不含拆放非银） | C13: 资产 | D13: 7000 | E13: =SUMPRODUCT(折现数据源!M$4:M$67,折现数据源!$D$4:$D$67) | F13: =SUMPRODUCT(折现数据源!M$4:M$67,折现数据源!$D$4:$D$67,折现数据源!$B$4:$B$67) | G13: =IF(E13=0,0,F13/E13) | H13: =IF(I13=0,G13,G13/(1+I13)) | I13: =IF(E13=0,0,SUMPRODUCT(折现数据源!M$4:M$67,折现数据源!$C$4:$C$67/100,折现数据源!$D$4:$D$67)/E13) | J13: =IF(SUM($E$5:$E$28)=0,0,E13/SUM($E$5:$E$28))
A14: S01010204000000 | B14: 2.4. 存款准备金 | C14: 资产 | D14: 3000 | E14: =SUMPRODUCT(折现数据源!N$4:N$67,折现数据源!$D$4:$D$67) | F14: =SUMPRODUCT(折现数据源!N$4:N$67,折现数据源!$D$4:$D$67,折现数据源!$B$4:$B$67) | G14: =IF(E14=0,0,F14/E14) | H14: =IF(I14=0,G14,G14/(1+I14)) | I14: =IF(E14=0,0,SUMPRODUCT(折现数据源!N$4:N$67,折现数据源!$C$4:$C$67/100,折现数据源!$D$4:$D$67)/E14) | J14: =IF(SUM($E$5:$E$28)=0,0,E14/SUM($E$5:$E$28))
A15: S01010301000000 | B15: 3.1. FVTPL类资产 | C15: 资产 | D15: 3000 | E15: =SUMPRODUCT(折现数据源!O$4:O$67,折现数据源!$D$4:$D$67) | F15: =SUMPRODUCT(折现数据源!O$4:O$67,折现数据源!$D$4:$D$67,折现数据源!$B$4:$B$67) | G15: =IF(E15=0,0,F15/E15) | H15: =IF(I15=0,G15,G15/(1+I15)) | I15: =IF(E15=0,0,SUMPRODUCT(折现数据源!O$4:O$67,折现数据源!$C$4:$C$67/100,折现数据源!$D$4:$D$67)/E15) | J15: =IF(SUM($E$5:$E$28)=0,0,E15/SUM($E$5:$E$28))
A16: S01010302000000 | B16: 3.2. 其他非生息资产 | C16: 资产 | D16: 2000 | E16: =SUMPRODUCT(折现数据源!P$4:P$67,折现数据源!$D$4:$D$67) | F16: =SUMPRODUCT(折现数据源!P$4:P$67,折现数据源!$D$4:$D$67,折现数据源!$B$4:$B$67) | G16: =IF(E16=0,0,F16/E16) | H16: =IF(I16=0,G16,G16/(1+I16)) | I16: =IF(E16=0,0,SUMPRODUCT(折现数据源!P$4:P$67,折现数据源!$C$4:$C$67/100,折现数据源!$D$4:$D$67)/E16) | J16: =IF(SUM($E$5:$E$28)=0,0,E16/SUM($E$5:$E$28))
A17: S01020100000000 | B17: 1. 外币贷款 | C17: 资产 | D17: 4000 | E17: =SUMPRODUCT(折现数据源!Q$4:Q$67,折现数据源!$D$4:$D$67) | F17: =SUMPRODUCT(折现数据源!Q$4:Q$67,折现数据源!$D$4:$D$67,折现数据源!$B$4:$B$67) | G17: =IF(E17=0,0,F17/E17) | H17: =IF(I17=0,G17,G17/(1+I17)) | I17: =IF(E17=0,0,SUMPRODUCT(折现数据源!Q$4:Q$67,折现数据源!$C$4:$C$67/100,折现数据源!$D$4:$D$67)/E17) | J17: =IF(SUM($E$5:$E$28)=0,0,E17/SUM($E$5:$E$28))
A18: S01020201000000 | B18: 2.1. 外币债券 | C18: 资产 | D18: 2000 | E18: =SUMPRODUCT(折现数据源!R$4:R$67,折现数据源!$D$4:$D$67) | F18: =SUMPRODUCT(折现数据源!R$4:R$67,折现数据源!$D$4:$D$67,折现数据源!$B$4:$B$67) | G18: =IF(E18=0,0,F18/E18) | H18: =IF(I18=0,G18,G18/(1+I18)) | I18: =IF(E18=0,0,SUMPRODUCT(折现数据源!R$4:R$67,折现数据源!$C$4:$C$67/100,折现数据源!$D$4:$D$67)/E18) | J18: =IF(SUM($E$5:$E$28)=0,0,E18/SUM($E$5:$E$28))
A19: S01020202000000 | B19: 2.2. 同业资产 | C19: 资产 | D19: 1000 | E19: =SUMPRODUCT(折现数据源!S$4:S$67,折现数据源!$D$4:$D$67) | F19: =SUMPRODUCT(折现数据源!S$4:S$67,折现数据源!$D$4:$D$67,折现数据源!$B$4:$B$67) | G19: =IF(E19=0,0,F19/E19) | H19: =IF(I19=0,G19,G19/(1+I19)) | I19: =IF(E19=0,0,SUMPRODUCT(折现数据源!S$4:S$67,折现数据源!$C$4:$C$67/100,折现数据源!$D$4:$D$67)/E19) | J19: =IF(SUM($E$5:$E$28)=0,0,E19/SUM($E$5:$E$28))
A20: S01020300000000 | B20: 3. 外币非生息资产 | C20: 资产 | D20: 1000 | E20: =SUMPRODUCT(折现数据源!T$4:T$67,折现数据源!$D$4:$D$67) | F20: =SUMPRODUCT(折现数据源!T$4:T$67,折现数据源!$D$4:$D$67,折现数据源!$B$4:$B$67) | G20: =IF(E20=0,0,F20/E20) | H20: =IF(I20=0,G20,G20/(1+I20)) | I20: =IF(E20=0,0,SUMPRODUCT(折现数据源!T$4:T$67,折现数据源!$C$4:$C$67/100,折现数据源!$D$4:$D$67)/E20) | J20: =IF(SUM($E$5:$E$28)=0,0,E20/SUM($E$5:$E$28))
A21: S020101010100 | B21: 1.1.1 对公活期存款 | C21: 负债 | D21: 26000 | E21: =SUMPRODUCT(折现数据源!U$4:U$67,折现数据源!$D$4:$D$67) | F21: =SUMPRODUCT(折现数据源!U$4:U$67,折现数据源!$D$4:$D$67,折现数据源!$B$4:$B$67) | G21: =IF(E21=0,0,F21/E21) | H21: =IF(I21=0,G21,G21/(1+I21)) | I21: =IF(E21=0,0,SUMPRODUCT(折现数据源!U$4:U$67,折现数据源!$C$4:$C$67/100,折现数据源!$D$4:$D$67)/E21) | J21: =IF(SUM($E$5:$E$28)=0,0,E21/SUM($E$5:$E$28))
A22: S020101010200 | B22: 1.1.2 对公定期存款 | C22: 负债 | D22: 22000 | E22: =SUMPRODUCT(折现数据源!V$4:V$67,折现数据源!$D$4:$D$67) | F22: =SUMPRODUCT(折现数据源!V$4:V$67,折现数据源!$D$4:$D$67,折现数据源!$B$4:$B$67) | G22: =IF(E22=0,0,F22/E22) | H22: =IF(I22=0,G22,G22/(1+I22)) | I22: =IF(E22=0,0,SUMPRODUCT(折现数据源!V$4:V$67,折现数据源!$C$4:$C$67/100,折现数据源!$D$4:$D$67)/E22) | J22: =IF(SUM($E$5:$E$28)=0,0,E22/SUM($E$5:$E$28))
A23: S020101020100 | B23: 1.2.1 零售活期存款 | C23: 负债 | D23: 12000 | E23: =SUMPRODUCT(折现数据源!W$4:W$67,折现数据源!$D$4:$D$67) | F23: =SUMPRODUCT(折现数据源!W$4:W$67,折现数据源!$D$4:$D$67,折现数据源!$B$4:$B$67) | G23: =IF(E23=0,0,F23/E23) | H23: =IF(I23=0,G23,G23/(1+I23)) | I23: =IF(E23=0,0,SUMPRODUCT(折现数据源!W$4:W$67,折现数据源!$C$4:$C$67/100,折现数据源!$D$4:$D$67)/E23) | J23: =IF(SUM($E$5:$E$28)=0,0,E23/SUM($E$5:$E$28))
A24: S020101020200 | B24: 1.2.2 零售定期存款 | C24: 负债 | D24: 20000 | E24: =SUMPRODUCT(折现数据源!X$4:X$67,折现数据源!$D$4:$D$67) | F24: =SUMPRODUCT(折现数据源!X$4:X$67,折现数据源!$D$4:$D$67,折现数据源!$B$4:$B$67) | G24: =IF(E24=0,0,F24/E24) | H24: =IF(I24=0,G24,G24/(1+I24)) | I24: =IF(E24=0,0,SUMPRODUCT(折现数据源!X$4:X$67,折现数据源!$C$4:$C$67/100,折现数据源!$D$4:$D$67)/E24) | J24: =IF(SUM($E$5:$E$28)=0,0,E24/SUM($E$5:$E$28))
A25: S02010200000000 | B25: 2. 人民币市场化负债 | C25: 负债 | D25: 12000 | E25: =SUMPRODUCT(折现数据源!Y$4:Y$67,折现数据源!$D$4:$D$67) | F25: =SUMPRODUCT(折现数据源!Y$4:Y$67,折现数据源!$D$4:$D$67,折现数据源!$B$4:$B$67) | G25: =IF(E25=0,0,F25/E25) | H25: =IF(I25=0,G25,G25/(1+I25)) | I25: =IF(E25=0,0,SUMPRODUCT(折现数据源!Y$4:Y$67,折现数据源!$C$4:$C$67/100,折现数据源!$D$4:$D$67)/E25) | J25: =IF(SUM($E$5:$E$28)=0,0,E25/SUM($E$5:$E$28))
A26: S02020100000000 | B26: 1. 外币存款 | C26: 负债 | D26: 4000 | E26: =SUMPRODUCT(折现数据源!Z$4:Z$67,折现数据源!$D$4:$D$67) | F26: =SUMPRODUCT(折现数据源!Z$4:Z$67,折现数据源!$D$4:$D$67,折现数据源!$B$4:$B$67) | G26: =IF(E26=0,0,F26/E26) | H26: =IF(I26=0,G26,G26/(1+I26)) | I26: =IF(E26=0,0,SUMPRODUCT(折现数据源!Z$4:Z$67,折现数据源!$C$4:$C$67/100,折现数据源!$D$4:$D$67)/E26) | J26: =IF(SUM($E$5:$E$28)=0,0,E26/SUM($E$5:$E$28))
A27: S02020200000000 | B27: 2. 外币市场化负债 | C27: 负债 | D27: 2000 | E27: =SUMPRODUCT(折现数据源!AA$4:AA$67,折现数据源!$D$4:$D$67) | F27: =SUMPRODUCT(折现数据源!AA$4:AA$67,折现数据源!$D$4:$D$67,折现数据源!$B$4:$B$67) | G27: =IF(E27=0,0,F27/E27) | H27: =IF(I27=0,G27,G27/(1+I27)) | I27: =IF(E27=0,0,SUMPRODUCT(折现数据源!AA$4:AA$67,折现数据源!$C$4:$C$67/100,折现数据源!$D$4:$D$67)/E27) | J27: =IF(SUM($E$5:$E$28)=0,0,E27/SUM($E$5:$E$28))
A28: S03000000000000 | B28: 所有者权益 | C28: 权益 | D28: 10000 | E28: =SUMPRODUCT(折现数据源!AB$4:AB$67,折现数据源!$D$4:$D$67) | F28: =SUMPRODUCT(折现数据源!AB$4:AB$67,折现数据源!$D$4:$D$67,折现数据源!$B$4:$B$67) | G28: =IF(E28=0,0,F28/E28) | H28: =IF(I28=0,G28,G28/(1+I28)) | I28: =IF(E28=0,0,SUMPRODUCT(折现数据源!AB$4:AB$67,折现数据源!$C$4:$C$67/100,折现数据源!$D$4:$D$67)/E28) | J28: =IF(SUM($E$5:$E$28)=0,0,E28/SUM($E$5:$E$28))
A29: 组合汇总
E30: =SUMIF($C$5:$C$28,"资产",$E$5:$E$28) | F30: =SUMIF($C$5:$C$28,"资产",$F$5:$F$28) | G30: =IF(E30=0,0,F30/E30) | H30: =IF(I30=0,G30,G30/(1+I30)) | I30: =IF(E30=0,0,SUMPRODUCT(($C$5:$C$28="资产")*$I$5:$I$28*$E$5:$E$28)/E30) | J30: =IF(SUM($E$5:$E$28)=0,0,E30/SUM($E$5:$E$28))
E31: =SUMIF($C$5:$C$28,"负债",$E$5:$E$28) | F31: =SUMIF($C$5:$C$28,"负债",$F$5:$F$28) | G31: =IF(E31=0,0,F31/E31) | H31: =IF(I31=0,G31,G31/(1+I31)) | I31: =IF(E31=0,0,SUMPRODUCT(($C$5:$C$28="负债")*$I$5:$I$28*$E$5:$E$28)/E31) | J31: =IF(SUM($E$5:$E$28)=0,0,E31/SUM($E$5:$E$28))
E32: =SUMIF($C$5:$C$28,"权益",$E$5:$E$28) | F32: =SUMIF($C$5:$C$28,"权益",$F$5:$F$28) | G32: =IF(E32=0,0,F32/E32) | H32: =IF(I32=0,G32,G32/(1+I32)) | I32: =IF(E32=0,0,SUMPRODUCT(($C$5:$C$28="权益")*$I$5:$I$28*$E$5:$E$28)/E32) | J32: =IF(SUM($E$5:$E$28)=0,0,E32/SUM($E$5:$E$28))
E33: DA - DL | G33: =G30-G31 | H33: =H30-H31

Sheet 久期缺口与敏感性
A1: 久期缺口 (Duration Gap) 与 NII 利率敏感性
A2: GAP = DA - DL | ΔNII/NII ≈ -GAP × Δr | 引用「麦考林久期计算表」汇总行，联动更新
A4: 情景 | B4: Δr (%) | C4: 资产久期 DA (年) | D4: 负债久期 DL (年) | E4: 久期缺口 GAP (年) | F4: NII 敏感度 (%) | G4: 说明
A5: 基准情景 | B5: 0 | C5: ='麦考林久期计算表'!G30 | D5: ='麦考林久期计算表'!G31 | E5: =C5-D5 | F5: =-E5*B5/100*100 | G5: 基准, 无冲击
A6: 平行上移 250bp | B6: 2.5 | C6: ='麦考林久期计算表'!G30 | D6: ='麦考林久期计算表'!G31 | E6: =C6-D6 | F6: =-E6*B6/100*100 | G6: 利率上行 → 正缺口银行 NII 受损
A7: 平行下移 250bp | B7: -2.5 | C7: ='麦考林久期计算表'!G30 | D7: ='麦考林久期计算表'!G31 | E7: =C7-D7 | F7: =-E7*B7/100*100 | G7: 利率下行 → 正缺口银行 NII 受益
A8: 变陡峭 | B8: 0.5 | C8: ='麦考林久期计算表'!G30 | D8: ='麦考林久期计算表'!G31 | E8: =C8-D8 | F8: =-E8*B8/100*100 | G8: 长期利率上行, 加权 Δr ≈ +50bp
A9: 变平坦 | B9: -0.5 | C9: ='麦考林久期计算表'!G30 | D9: ='麦考林久期计算表'!G31 | E9: =C9-D9 | F9: =-E9*B9/100*100 | G9: 短期利率下行, 加权 Δr ≈ -50bp
A12: 久期缺口解读 (自动联动)
A13: 久期缺口类型 | B13: =IF('麦考林久期计算表'!$G$33>0,"正缺口 (资产久期 > 负债久期)",IF('麦考林久期计算表'!$G$33<0,"负缺口 (资产久期 < 负债久期)","零缺口"))
A14: GAP 值 | B14: =TEXT('麦考林久期计算表'!$G$33,"+0.0000;-0.0000")&" 年"
A15: 利率 +25bp 的 NII 影响 | B15: =TEXT(-'麦考林久期计算表'!$G$33*0.025*100,"+0.0000")&"% ("&IF(-'麦考林久期计算表'!$G$33>0,"NII 受损","NII 受益")&")"
A16: 利率 -25bp 的 NII 影响 | B16: =TEXT('麦考林久期计算表'!$G$33*0.025*100,"+0.0000")&"% ("&IF('麦考林久期计算表'!$G$33>0,"NII 受损","NII 受益")&")"
A17: 管理含义 | B17: =IF('麦考林久期计算表'!$G$33>0,"正缺口银行: 利率上行期重定价压力, 需通过拉长久期负债或配置长久期资产对冲","负缺口银行: 利率下行期承压, 负债重定价快于资产, 建议缩短资产久期")
A18: 调节手段 | B18: ① 发行长期同业存单 / 金融债拉长久期负债 ② 配置长久期债券 / 拉长久期贷款 ③ 利率衍生品对冲 (国债期货 / 利率互换)

Sheet 期限分布分析
A1: 现金流期限分布 (按 PV 汇总) — 久期成因拆解
A2: Σ 各账户现金流 × 折现因子, 按期限汇总 | 引用「折现数据源」sheet，联动更新
A4: 期限 | B4: 年数 (t) | C4: 利率 (%) | D4: 折现因子 | E4: 资产 PV (亿元) | F4: 负债 PV (亿元) | G4: 资产 PV 占比 (%) | H4: 累计占比 (%)
A5: =折现数据源!A4 | B5: =折现数据源!B4 | C5: =折现数据源!C4 | D5: =折现数据源!D4 | E5: =SUMPRODUCT(折现数据源!E$4:E$67,折现数据源!$D$4:$D$67)+SUMPRODUCT(折现数据源!F$4:F$67,折现数据源!$D$4:$D$67)+SUMPRODUCT(折现数据源!G$4:G$67,折现数据源!$D$4:$D$67)+SUMPRODUCT(折现数据源!H$4:H$67,折现数据源!$D$4:$D$67)+SUMPRODUCT(折现数据源!I$4:I$67,折现数据源!$D$4:$D$67)+SUMPRODUCT(折现数据源!J$4:J$67,折现数据源!$D$4:$D$67)+SUMPRODUCT(折现数据源!K$4:K$67,折现数据源!$D$4:$D$67)+SUMPRODUCT(折现数据源!L$4:L$67,折现数据源!$D$4:$D$67)+SUMPRODUCT(折现数据源!M$4:M$67,折现数据源!$D$4:$D$67)+SUMPRODUCT(折现数据源!N$4:N$67,折现数据源!$D$4:$D$67)+SUMPRODUCT(折现数据源!O$4:O$67,折现数据源!$D$4:$D$67)+SUMPRODUCT(折现数据源!P$4:P$67,折现数据源!$D$4:$D$67)+SUMPRODUCT(折现数据源!Q$4:Q$67,折现数据源!$D$4:$D$67)+SUMPRODUCT(折现数据源!R$4:R$67,折现数据源!$D$4:$D$67)+SUMPRODUCT(折现数据源!S$4:S$67,折现数据源!$D$4:$D$67)+SUMPRODUCT(折现数据源!T$4:T$67,折现数据源!$D$4:$D$67) | F5: =SUMPRODUCT(折现数据源!U$4:U$67,折现数据源!$D$4:$D$67)+SUMPRODUCT(折现数据源!V$4:V$67,折现数据源!$D$4:$D$67)+SUMPRODUCT(折现数据源!W$4:W$67,折现数据源!$D$4:$D$67)+SUMPRODUCT(折现数据源!X$4:X$67,折现数据源!$D$4:$D$67)+SUMPRODUCT(折现数据源!Y$4:Y$67,折现数据源!$D$4:$D$67)+SUMPRODUCT(折现数据源!Z$4:Z$67,折现数据源!$D$4:$D$67)+SUMPRODUCT(折现数据源!AA$4:AA$67,折现数据源!$D$4:$D$67) | G5: =IF(SUM($E$5:$E$68)=0,0,E5/SUM($E$5:$E$68)) | H5: =G5
A6: =折现数据源!A5 | B6: =折现数据源!B5 | C6: =折现数据源!C5 | D6: =折现数据源!D5 | E6: =SUMPRODUCT(折现数据源!E$4:E$67,折现数据源!$D$4:$D$67)+SUMPRODUCT(折现数据源!F$4:F$67,折现数据源!$D$4:$D$67)+SUMPRODUCT(折现数据源!G$4:G$67,折现数据源!$D$4:$D$67)+SUMPRODUCT(折现数据源!H$4:H$67,折现数据源!$D$4:$D$67)+SUMPRODUCT(折现数据源!I$4:I$67,折现数据源!$D$4:$D$67)+SUMPRODUCT(折现数据源!J$4:J$67,折现数据源!$D$4:$D$67)+SUMPRODUCT(折现数据源!K$4:K$67,折现数据源!$D$4:$D$67)+SUMPRODUCT(折现数据源!L$4:L$67,折现数据源!$D$4:$D$67)+SUMPRODUCT(折现数据源!M$4:M$67,折现数据源!$D$4:$D$67)+SUMPRODUCT(折现数据源!N$4:N$67,折现数据源!$D$4:$D$67)+SUMPRODUCT(折现数据源!O$4:O$67,折现数据源!$D$4:$D$67)+SUMPRODUCT(折现数据源!P$4:P$67,折现数据源!$D$4:$D$67)+SUMPRODUCT(折现数据源!Q$4:Q$67,折现数据源!$D$4:$D$67)+SUMPRODUCT(折现数据源!R$4:R$67,折现数据源!$D$4:$D$67)+SUMPRODUCT(折现数据源!S$4:S$67,折现数据源!$D$4:$D$67)+SUMPRODUCT(折现数据源!T$4:T$67,折现数据源!$D$4:$D$67) | F6: =SUMPRODUCT(折现数据源!U$4:U$67,折现数据源!$D$4:$D$67)+SUMPRODUCT(折现数据源!V$4:V$67,折现数据源!$D$4:$D$67)+SUMPRODUCT(折现数据源!W$4:W$67,折现数据源!$D$4:$D$67)+SUMPRODUCT(折现数据源!X$4:X$67,折现数据源!$D$4:$D$67)+SUMPRODUCT(折现数据源!Y$4:Y$67,折现数据源!$D$4:$D$67)+SUMPRODUCT(折现数据源!Z$4:Z$67,折现数据源!$D$4:$D$67)+SUMPRODUCT(折现数据源!AA$4:AA$67,折现数据源!$D$4:$D$67) | G6: =IF(SUM($E$5:$E$68)=0,0,E6/SUM($E$5:$E$68)) | H6: =H5+G6
A7: =折现数据源!A6 | B7: =折现数据源!B6 | C7: =折现数据源!C6 | D7: =折现数据源!D6 | E7: =SUMPRODUCT(折现数据源!E$4:E$67,折现数据源!$D$4:$D$67)+SUMPRODUCT(折现数据源!F$4:F$67,折现数据源!$D$4:$D$67)+SUMPRODUCT(折现数据源!G$4:G$67,折现数据源!$D$4:$D$67)+SUMPRODUCT(折现数据源!H$4:H$67,折现数据源!$D$4:$D$67)+SUMPRODUCT(折现数据源!I$4:I$67,折现数据源!$D$4:$D$67)+SUMPRODUCT(折现数据源!J$4:J$67,折现数据源!$D$4:$D$67)+SUMPRODUCT(折现数据源!K$4:K$67,折现数据源!$D$4:$D$67)+SUMPRODUCT(折现数据源!L$4:L$67,折现数据源!$D$4:$D$67)+SUMPRODUCT(折现数据源!M$4:M$67,折现数据源!$D$4:$D$67)+SUMPRODUCT(折现数据源!N$4:N$67,折现数据源!$D$4:$D$67)+SUMPRODUCT(折现数据源!O$4:O$67,折现数据源!$D$4:$D$67)+SUMPRODUCT(折现数据源!P$4:P$67,折现数据源!$D$4:$D$67)+SUMPRODUCT(折现数据源!Q$4:Q$67,折现数据源!$D$4:$D$67)+SUMPRODUCT(折现数据源!R$4:R$67,折现数据源!$D$4:$D$67)+SUMPRODUCT(折现数据源!S$4:S$67,折现数据源!$D$4:$D$67)+SUMPRODUCT(折现数据源!T$4:T$67,折现数据源!$D$4:$D$67) | F7: =SUMPRODUCT(折现数据源!U$4:U$67,折现数据源!$D$4:$D$67)+SUMPRODUCT(折现数据源!V$4:V$67,折现数据源!$D$4:$D$67)+SUMPRODUCT(折现数据源!W$4:W$67,折现数据源!$D$4:$D$67)+SUMPRODUCT(折现数据源!X$4:X$67,折现数据源!$D$4:$D$67)+SUMPRODUCT(折现数据源!Y$4:Y$67,折现数据源!$D$4:$D$67)+SUMPRODUCT(折现数据源!Z$4:Z$67,折现数据源!$D$4:$D$67)+SUMPRODUCT(折现数据源!AA$4:AA$67,折现数据源!$D$4:$D$67) | G7: =IF(SUM($E$5:$E$68)=0,0,E7/SUM($E$5:$E$68)) | H7: =H6+G7
A8: =折现数据源!A7 | B8: =折现数据源!B7 | C8: =折现数据源!C7 | D8: =折现数据源!D7 | E8: =SUMPRODUCT(折现数据源!E$4:E$67,折现数据源!$D$4:$D$67)+SUMPRODUCT(折现数据源!F$4:F$67,折现数据源!$D$4:$D$67)+SUMPRODUCT(折现数据源!G$4:G$67,折现数据源!$D$4:$D$67)+SUMPRODUCT(折现数据源!H$4:H$67,折现数据源!$D$4:$D$67)+SUMPRODUCT(折现数据源!I$4:I$67,折现数据源!$D$4:$D$67)+SUMPRODUCT(折现数据源!J$4:J$67,折现数据源!$D$4:$D$67)+SUMPRODUCT(折现数据源!K$4:K$67,折现数据源!$D$4:$D$67)+SUMPRODUCT(折现数据源!L$4:L$67,折现数据源!$D$4:$D$67)+SUMPRODUCT(折现数据源!M$4:M$67,折现数据源!$D$4:$D$67)+SUMPRODUCT(折现数据源!N$4:N$67,折现数据源!$D$4:$D$67)+SUMPRODUCT(折现数据源!O$4:O$67,折现数据源!$D$4:$D$67)+SUMPRODUCT(折现数据源!P$4:P$67,折现数据源!$D$4:$D$67)+SUMPRODUCT(折现数据源!Q$4:Q$67,折现数据源!$D$4:$D$67)+SUMPRODUCT(折现数据源!R$4:R$67,折现数据源!$D$4:$D$67)+SUMPRODUCT(折现数据源!S$4:S$67,折现数据源!$D$4:$D$67)+SUMPRODUCT(折现数据源!T$4:T$67,折现数据源!$D$4:$D$67) | F8: =SUMPRODUCT(折现数据源!U$4:U$67,折现数据源!$D$4:$D$67)+SUMPRODUCT(折现数据源!V$4:V$67,折现数据源!$D$4:$D$67)+SUMPRODUCT(折现数据源!W$4:W$67,折现数据源!$D$4:$D$67)+SUMPRODUCT(折现数据源!X$4:X$67,折现数据源!$D$4:$D$67)+SUMPRODUCT(折现数据源!Y$4:Y$67,折现数据源!$D$4:$D$67)+SUMPRODUCT(折现数据源!Z$4:Z$67,折现数据源!$D$4:$D$67)+SUMPRODUCT(折现数据源!AA$4:AA$67,折现数据源!$D$4:$D$67) | G8: =IF(SUM($E$5:$E$68)=0,0,E8/SUM($E$5:$E$68)) | H8: =H7+G8
A9: =折现数据源!A8 | B9: =折现数据源!B8 | C9: =折现数据源!C8 | D9: =折现数据源!D8 | E9: =SUMPRODUCT(折现数据源!E$4:E$67,折现数据源!$D$4:$D$67)+SUMPRODUCT(折现数据源!F$4:F$67,折现数据源!$D$4:$D$67)+SUMPRODUCT(折现数据源!G$4:G$67,折现数据源!$D$4:$D$67)+SUMPRODUCT(折现数据源!H$4:H$67,折现数据源!$D$4:$D$67)+SUMPRODUCT(折现数据源!I$4:I$67,折现数据源!$D$4:$D$67)+SUMPRODUCT(折现数据源!J$4:J$67,折现数据源!$D$4:$D$67)+SUMPRODUCT(折现数据源!K$4:K$67,折现数据源!$D$4:$D$67)+SUMPRODUCT(折现数据源!L$4:L$67,折现数据源!$D$4:$D$67)+SUMPRODUCT(折现数据源!M$4:M$67,折现数据源!$D$4:$D$67)+SUMPRODUCT(折现数据源!N$4:N$67,折现数据源!$D$4:$D$67)+SUMPRODUCT(折现数据源!O$4:O$67,折现数据源!$D$4:$D$67)+SUMPRODUCT(折现数据源!P$4:P$67,折现数据源!$D$4:$D$67)+SUMPRODUCT(折现数据源!Q$4:Q$67,折现数据源!$D$4:$D$67)+SUMPRODUCT(折现数据源!R$4:R$67,折现数据源!$D$4:$D$67)+SUMPRODUCT(折现数据源!S$4:S$67,折现数据源!$D$4:$D$67)+SUMPRODUCT(折现数据源!T$4:T$67,折现数据源!$D$4:$D$67) | F9: =SUMPRODUCT(折现数据源!U$4:U$67,折现数据源!$D$4:$D$67)+SUMPRODUCT(折现数据源!V$4:V$67,折现数据源!$D$4:$D$67)+SUMPRODUCT(折现数据源!W$4:W$67,折现数据源!$D$4:$D$67)+SUMPRODUCT(折现数据源!X$4:X$67,折现数据源!$D$4:$D$67)+SUMPRODUCT(折现数据源!Y$4:Y$67,折现数据源!$D$4:$D$67)+SUMPRODUCT(折现数据源!Z$4:Z$67,折现数据源!$D$4:$D$67)+SUMPRODUCT(折现数据源!AA$4:AA$67,折现数据源!$D$4:$D$67) | G9: =IF(SUM($E$5:$E$68)=0,0,E9/SUM($E$5:$E$68)) | H9: =H8+G9
A10: =折现数据源!A9 | B10: =折现数据源!B9 | C10: =折现数据源!C9 | D10: =折现数据源!D9 | E10: =SUMPRODUCT(折现数据源!E$4:E$67,折现数据源!$D$4:$D$67)+SUMPRODUCT(折现数据源!F$4:F$67,折现数据源!$D$4:$D$67)+SUMPRODUCT(折现数据源!G$4:G$67,折现数据源!$D$4:$D$67)+SUMPRODUCT(折现数据源!H$4:H$67,折现数据源!$D$4:$D$67)+SUMPRODUCT(折现数据源!I$4:I$67,折现数据源!$D$4:$D$67)+SUMPRODUCT(折现数据源!J$4:J$67,折现数据源!$D$4:$D$67)+SUMPRODUCT(折现数据源!K$4:K$67,折现数据源!$D$4:$D$67)+SUMPRODUCT(折现数据源!L$4:L$67,折现数据源!$D$4:$D$67)+SUMPRODUCT(折现数据源!M$4:M$67,折现数据源!$D$4:$D$67)+SUMPRODUCT(折现数据源!N$4:N$67,折现数据源!$D$4:$D$67)+SUMPRODUCT(折现数据源!O$4:O$67,折现数据源!$D$4:$D$67)+SUMPRODUCT(折现数据源!P$4:P$67,折现数据源!$D$4:$D$67)+SUMPRODUCT(折现数据源!Q$4:Q$67,折现数据源!$D$4:$D$67)+SUMPRODUCT(折现数据源!R$4:R$67,折现数据源!$D$4:$D$67)+SUMPRODUCT(折现数据源!S$4:S$67,折现数据源!$D$4:$D$67)+SUMPRODUCT(折现数据源!T$4:T$67,折现数据源!$D$4:$D$67) | F10: =SUMPRODUCT(折现数据源!U$4:U$67,折现数据源!$D$4:$D$67)+SUMPRODUCT(折现数据源!V$4:V$67,折现数据源!$D$4:$D$67)+SUMPRODUCT(折现数据源!W$4:W$67,折现数据源!$D$4:$D$67)+SUMPRODUCT(折现数据源!X$4:X$67,折现数据源!$D$4:$D$67)+SUMPRODUCT(折现数据源!Y$4:Y$67,折现数据源!$D$4:$D$67)+SUMPRODUCT(折现数据源!Z$4:Z$67,折现数据源!$D$4:$D$67)+SUMPRODUCT(折现数据源!AA$4:AA$67,折现数据源!$D$4:$D$67) | G10: =IF(SUM($E$5:$E$68)=0,0,E10/SUM($E$5:$E$68)) | H10: =H9+G10
A11: =折现数据源!A10 | B11: =折现数据源!B10 | C11: =折现数据源!C10 | D11: =折现数据源!D10 | E11: =SUMPRODUCT(折现数据源!E$4:E$67,折现数据源!$D$4:$D$67)+SUMPRODUCT(折现数据源!F$4:F$67,折现数据源!$D$4:$D$67)+SUMPRODUCT(折现数据源!G$4:G$67,折现数据源!$D$4:$D$67)+SUMPRODUCT(折现数据源!H$4:H$67,折现数据源!$D$4:$D$67)+SUMPRODUCT(折现数据源!I$4:I$67,折现数据源!$D$4:$D$67)+SUMPRODUCT(折现数据源!J$4:J$67,折现数据源!$D$4:$D$67)+SUMPRODUCT(折现数据源!K$4:K$67,折现数据源!$D$4:$D$67)+SUMPRODUCT(折现数据源!L$4:L$67,折现数据源!$D$4:$D$67)+SUMPRODUCT(折现数据源!M$4:M$67,折现数据源!$D$4:$D$67)+SUMPRODUCT(折现数据源!N$4:N$67,折现数据源!$D$4:$D$67)+SUMPRODUCT(折现数据源!O$4:O$67,折现数据源!$D$4:$D$67)+SUMPRODUCT(折现数据源!P$4:P$67,折现数据源!$D$4:$D$67)+SUMPRODUCT(折现数据源!Q$4:Q$67,折现数据源!$D$4:$D$67)+SUMPRODUCT(折现数据源!R$4:R$67,折现数据源!$D$4:$D$67)+SUMPRODUCT(折现数据源!S$4:S$67,折现数据源!$D$4:$D$67)+SUMPRODUCT(折现数据源!T$4:T$67,折现数据源!$D$4:$D$67) | F11: =SUMPRODUCT(折现数据源!U$4:U$67,折现数据源!$D$4:$D$67)+SUMPRODUCT(折现数据源!V$4:V$67,折现数据源!$D$4:$D$67)+SUMPRODUCT(折现数据源!W$4:W$67,折现数据源!$D$4:$D$67)+SUMPRODUCT(折现数据源!X$4:X$67,折现数据源!$D$4:$D$67)+SUMPRODUCT(折现数据源!Y$4:Y$67,折现数据源!$D$4:$D$67)+SUMPRODUCT(折现数据源!Z$4:Z$67,折现数据源!$D$4:$D$67)+SUMPRODUCT(折现数据源!AA$4:AA$67,折现数据源!$D$4:$D$67) | G11: =IF(SUM($E$5:$E$68)=0,0,E11/SUM($E$5:$E$68)) | H11: =H10+G11
A12: =折现数据源!A11 | B12: =折现数据源!B11 | C12: =折现数据源!C11 | D12: =折现数据源!D11 | E12: =SUMPRODUCT(折现数据源!E$4:E$67,折现数据源!$D$4:$D$67)+SUMPRODUCT(折现数据源!F$4:F$67,折现数据源!$D$4:$D$67)+SUMPRODUCT(折现数据源!G$4:G$67,折现数据源!$D$4:$D$67)+SUMPRODUCT(折现数据源!H$4:H$67,折现数据源!$D$4:$D$67)+SUMPRODUCT(折现数据源!I$4:I$67,折现数据源!$D$4:$D$67)+SUMPRODUCT(折现数据源!J$4:J$67,折现数据源!$D$4:$D$67)+SUMPRODUCT(折现数据源!K$4:K$67,折现数据源!$D$4:$D$67)+SUMPRODUCT(折现数据源!L$4:L$67,折现数据源!$D$4:$D$67)+SUMPRODUCT(折现数据源!M$4:M$67,折现数据源!$D$4:$D$67)+SUMPRODUCT(折现数据源!N$4:N$67,折现数据源!$D$4:$D$67)+SUMPRODUCT(折现数据源!O$4:O$67,折现数据源!$D$4:$D$67)+SUMPRODUCT(折现数据源!P$4:P$67,折现数据源!$D$4:$D$67)+SUMPRODUCT(折现数据源!Q$4:Q$67,折现数据源!$D$4:$D$67)+SUMPRODUCT(折现数据源!R$4:R$67,折现数据源!$D$4:$D$67)+SUMPRODUCT(折现数据源!S$4:S$67,折现数据源!$D$4:$D$67)+SUMPRODUCT(折现数据源!T$4:T$67,折现数据源!$D$4:$D$67) | F12: =SUMPRODUCT(折现数据源!U$4:U$67,折现数据源!$D$4:$D$67)+SUMPRODUCT(折现数据源!V$4:V$67,折现数据源!$D$4:$D$67)+SUMPRODUCT(折现数据源!W$4:W$67,折现数据源!$D$4:$D$67)+SUMPRODUCT(折现数据源!X$4:X$67,折现数据源!$D$4:$D$67)+SUMPRODUCT(折现数据源!Y$4:Y$67,折现数据源!$D$4:$D$67)+SUMPRODUCT(折现数据源!Z$4:Z$67,折现数据源!$D$4:$D$67)+SUMPRODUCT(折现数据源!AA$4:AA$67,折现数据源!$D$4:$D$67) | G12: =IF(SUM($E$5:$E$68)=0,0,E12/SUM($E$5:$E$68)) | H12: =H11+G12
A13: =折现数据源!A12 | B13: =折现数据源!B12 | C13: =折现数据源!C12 | D13: =折现数据源!D12 | E13: =SUMPRODUCT(折现数据源!E$4:E$67,折现数据源!$D$4:$D$67)+SUMPRODUCT(折现数据源!F$4:F$67,折现数据源!$D$4:$D$67)+SUMPRODUCT(折现数据源!G$4:G$67,折现数据源!$D$4:$D$67)+SUMPRODUCT(折现数据源!H$4:H$67,折现数据源!$D$4:$D$67)+SUMPRODUCT(折现数据源!I$4:I$67,折现数据源!$D$4:$D$67)+SUMPRODUCT(折现数据源!J$4:J$67,折现数据源!$D$4:$D$67)+SUMPRODUCT(折现数据源!K$4:K$67,折现数据源!$D$4:$D$67)+SUMPRODUCT(折现数据源!L$4:L$67,折现数据源!$D$4:$D$67)+SUMPRODUCT(折现数据源!M$4:M$67,折现数据源!$D$4:$D$67)+SUMPRODUCT(折现数据源!N$4:N$67,折现数据源!$D$4:$D$67)+SUMPRODUCT(折现数据源!O$4:O$67,折现数据源!$D$4:$D$67)+SUMPRODUCT(折现数据源!P$4:P$67,折现数据源!$D$4:$D$67)+SUMPRODUCT(折现数据源!Q$4:Q$67,折现数据源!$D$4:$D$67)+SUMPRODUCT(折现数据源!R$4:R$67,折现数据源!$D$4:$D$67)+SUMPRODUCT(折现数据源!S$4:S$67,折现数据源!$D$4:$D$67)+SUMPRODUCT(折现数据源!T$4:T$67,折现数据源!$D$4:$D$67) | F13: =SUMPRODUCT(折现数据源!U$4:U$67,折现数据源!$D$4:$D$67)+SUMPRODUCT(折现数据源!V$4:V$67,折现数据源!$D$4:$D$67)+SUMPRODUCT(折现数据源!W$4:W$67,折现数据源!$D$4:$D$67)+SUMPRODUCT(折现数据源!X$4:X$67,折现数据源!$D$4:$D$67)+SUMPRODUCT(折现数据源!Y$4:Y$67,折现数据源!$D$4:$D$67)+SUMPRODUCT(折现数据源!Z$4:Z$67,折现数据源!$D$4:$D$67)+SUMPRODUCT(折现数据源!AA$4:AA$67,折现数据源!$D$4:$D$67) | G13: =IF(SUM($E$5:$E$68)=0,0,E13/SUM($E$5:$E$68)) | H13: =H12+G13
A14: =折现数据源!A13 | B14: =折现数据源!B13 | C14: =折现数据源!C13 | D14: =折现数据源!D13 | E14: =SUMPRODUCT(折现数据源!E$4:E$67,折现数据源!$D$4:$D$67)+SUMPRODUCT(折现数据源!F$4:F$67,折现数据源!$D$4:$D$67)+SUMPRODUCT(折现数据源!G$4:G$67,折现数据源!$D$4:$D$67)+SUMPRODUCT(折现数据源!H$4:H$67,折现数据源!$D$4:$D$67)+SUMPRODUCT(折现数据源!I$4:I$67,折现数据源!$D$4:$D$67)+SUMPRODUCT(折现数据源!J$4:J$67,折现数据源!$D$4:$D$67)+SUMPRODUCT(折现数据源!K$4:K$67,折现数据源!$D$4:$D$67)+SUMPRODUCT(折现数据源!L$4:L$67,折现数据源!$D$4:$D$67)+SUMPRODUCT(折现数据源!M$4:M$67,折现数据源!$D$4:$D$67)+SUMPRODUCT(折现数据源!N$4:N$67,折现数据源!$D$4:$D$67)+SUMPRODUCT(折现数据源!O$4:O$67,折现数据源!$D$4:$D$67)+SUMPRODUCT(折现数据源!P$4:P$67,折现数据源!$D$4:$D$67)+SUMPRODUCT(折现数据源!Q$4:Q$67,折现数据源!$D$4:$D$67)+SUMPRODUCT(折现数据源!R$4:R$67,折现数据源!$D$4:$D$67)+SUMPRODUCT(折现数据源!S$4:S$67,折现数据源!$D$4:$D$67)+SUMPRODUCT(折现数据源!T$4:T$67,折现数据源!$D$4:$D$67) | F14: =SUMPRODUCT(折现数据源!U$4:U$67,折现数据源!$D$4:$D$67)+SUMPRODUCT(折现数据源!V$4:V$67,折现数据源!$D$4:$D$67)+SUMPRODUCT(折现数据源!W$4:W$67,折现数据源!$D$4:$D$67)+SUMPRODUCT(折现数据源!X$4:X$67,折现数据源!$D$4:$D$67)+SUMPRODUCT(折现数据源!Y$4:Y$67,折现数据源!$D$4:$D$67)+SUMPRODUCT(折现数据源!Z$4:Z$67,折现数据源!$D$4:$D$67)+SUMPRODUCT(折现数据源!AA$4:AA$67,折现数据源!$D$4:$D$67) | G14: =IF(SUM($E$5:$E$68)=0,0,E14/SUM($E$5:$E$68)) | H14: =H13+G14
A15: =折现数据源!A14 | B15: =折现数据源!B14 | C15: =折现数据源!C14 | D15: =折现数据源!D14 | E15: =SUMPRODUCT(折现数据源!E$4:E$67,折现数据源!$D$4:$D$67)+SUMPRODUCT(折现数据源!F$4:F$67,折现数据源!$D$4:$D$67)+SUMPRODUCT(折现数据源!G$4:G$67,折现数据源!$D$4:$D$67)+SUMPRODUCT(折现数据源!H$4:H$67,折现数据源!$D$4:$D$67)+SUMPRODUCT(折现数据源!I$4:I$67,折现数据源!$D$4:$D$67)+SUMPRODUCT(折现数据源!J$4:J$67,折现数据源!$D$4:$D$67)+SUMPRODUCT(折现数据源!K$4:K$67,折现数据源!$D$4:$D$67)+SUMPRODUCT(折现数据源!L$4:L$67,折现数据源!$D$4:$D$67)+SUMPRODUCT(折现数据源!M$4:M$67,折现数据源!$D$4:$D$67)+SUMPRODUCT(折现数据源!N$4:N$67,折现数据源!$D$4:$D$67)+SUMPRODUCT(折现数据源!O$4:O$67,折现数据源!$D$4:$D$67)+SUMPRODUCT(折现数据源!P$4:P$67,折现数据源!$D$4:$D$67)+SUMPRODUCT(折现数据源!Q$4:Q$67,折现数据源!$D$4:$D$67)+SUMPRODUCT(折现数据源!R$4:R$67,折现数据源!$D$4:$D$67)+SUMPRODUCT(折现数据源!S$4:S$67,折现数据源!$D$4:$D$67)+SUMPRODUCT(折现数据源!T$4:T$67,折现数据源!$D$4:$D$67) | F15: =SUMPRODUCT(折现数据源!U$4:U$67,折现数据源!$D$4:$D$67)+SUMPRODUCT(折现数据源!V$4:V$67,折现数据源!$D$4:$D$67)+SUMPRODUCT(折现数据源!W$4:W$67,折现数据源!$D$4:$D$67)+SUMPRODUCT(折现数据源!X$4:X$67,折现数据源!$D$4:$D$67)+SUMPRODUCT(折现数据源!Y$4:Y$67,折现数据源!$D$4:$D$67)+SUMPRODUCT(折现数据源!Z$4:Z$67,折现数据源!$D$4:$D$67)+SUMPRODUCT(折现数据源!AA$4:AA$67,折现数据源!$D$4:$D$67) | G15: =IF(SUM($E$5:$E$68)=0,0,E15/SUM($E$5:$E$68)) | H15: =H14+G15
A16: =折现数据源!A15 | B16: =折现数据源!B15 | C16: =折现数据源!C15 | D16: =折现数据源!D15 | E16: =SUMPRODUCT(折现数据源!E$4:E$67,折现数据源!$D$4:$D$67)+SUMPRODUCT(折现数据源!F$4:F$67,折现数据源!$D$4:$D$67)+SUMPRODUCT(折现数据源!G$4:G$67,折现数据源!$D$4:$D$67)+SUMPRODUCT(折现数据源!H$4:H$67,折现数据源!$D$4:$D$67)+SUMPRODUCT(折现数据源!I$4:I$67,折现数据源!$D$4:$D$67)+SUMPRODUCT(折现数据源!J$4:J$67,折现数据源!$D$4:$D$67)+SUMPRODUCT(折现数据源!K$4:K$67,折现数据源!$D$4:$D$67)+SUMPRODUCT(折现数据源!L$4:L$67,折现数据源!$D$4:$D$67)+SUMPRODUCT(折现数据源!M$4:M$67,折现数据源!$D$4:$D$67)+SUMPRODUCT(折现数据源!N$4:N$67,折现数据源!$D$4:$D$67)+SUMPRODUCT(折现数据源!O$4:O$67,折现数据源!$D$4:$D$67)+SUMPRODUCT(折现数据源!P$4:P$67,折现数据源!$D$4:$D$67)+SUMPRODUCT(折现数据源!Q$4:Q$67,折现数据源!$D$4:$D$67)+SUMPRODUCT(折现数据源!R$4:R$67,折现数据源!$D$4:$D$67)+SUMPRODUCT(折现数据源!S$4:S$67,折现数据源!$D$4:$D$67)+SUMPRODUCT(折现数据源!T$4:T$67,折现数据源!$D$4:$D$67) | F16: =SUMPRODUCT(折现数据源!U$4:U$67,折现数据源!$D$4:$D$67)+SUMPRODUCT(折现数据源!V$4:V$67,折现数据源!$D$4:$D$67)+SUMPRODUCT(折现数据源!W$4:W$67,折现数据源!$D$4:$D$67)+SUMPRODUCT(折现数据源!X$4:X$67,折现数据源!$D$4:$D$67)+SUMPRODUCT(折现数据源!Y$4:Y$67,折现数据源!$D$4:$D$67)+SUMPRODUCT(折现数据源!Z$4:Z$67,折现数据源!$D$4:$D$67)+SUMPRODUCT(折现数据源!AA$4:AA$67,折现数据源!$D$4:$D$67) | G16: =IF(SUM($E$5:$E$68)=0,0,E16/SUM($E$5:$E$68)) | H16: =H15+G16
A17: =折现数据源!A16 | B17: =折现数据源!B16 | C17: =折现数据源!C16 | D17: =折现数据源!D16 | E17: =SUMPRODUCT(折现数据源!E$4:E$67,折现数据源!$D$4:$D$67)+SUMPRODUCT(折现数据源!F$4:F$67,折现数据源!$D$4:$D$67)+SUMPRODUCT(折现数据源!G$4:G$67,折现数据源!$D$4:$D$67)+SUMPRODUCT(折现数据源!H$4:H$67,折现数据源!$D$4:$D$67)+SUMPRODUCT(折现数据源!I$4:I$67,折现数据源!$D$4:$D$67)+SUMPRODUCT(折现数据源!J$4:J$67,折现数据源!$D$4:$D$67)+SUMPRODUCT(折现数据源!K$4:K$67,折现数据源!$D$4:$D$67)+SUMPRODUCT(折现数据源!L$4:L$67,折现数据源!$D$4:$D$67)+SUMPRODUCT(折现数据源!M$4:M$67,折现数据源!$D$4:$D$67)+SUMPRODUCT(折现数据源!N$4:N$67,折现数据源!$D$4:$D$67)+SUMPRODUCT(折现数据源!O$4:O$67,折现数据源!$D$4:$D$67)+SUMPRODUCT(折现数据源!P$4:P$67,折现数据源!$D$4:$D$67)+SUMPRODUCT(折现数据源!Q$4:Q$67,折现数据源!$D$4:$D$67)+SUMPRODUCT(折现数据源!R$4:R$67,折现数据源!$D$4:$D$67)+SUMPRODUCT(折现数据源!S$4:S$67,折现数据源!$D$4:$D$67)+SUMPRODUCT(折现数据源!T$4:T$67,折现数据源!$D$4:$D$67) | F17: =SUMPRODUCT(折现数据源!U$4:U$67,折现数据源!$D$4:$D$67)+SUMPRODUCT(折现数据源!V$4:V$67,折现数据源!$D$4:$D$67)+SUMPRODUCT(折现数据源!W$4:W$67,折现数据源!$D$4:$D$67)+SUMPRODUCT(折现数据源!X$4:X$67,折现数据源!$D$4:$D$67)+SUMPRODUCT(折现数据源!Y$4:Y$67,折现数据源!$D$4:$D$67)+SUMPRODUCT(折现数据源!Z$4:Z$67,折现数据源!$D$4:$D$67)+SUMPRODUCT(折现数据源!AA$4:AA$67,折现数据源!$D$4:$D$67) | G17: =IF(SUM($E$5:$E$68)=0,0,E17/SUM($E$5:$E$68)) | H17: =H16+G17
... A68: =折现数据源!A67 | B68: =折现数据源!B67 | C68: =折现数据源!C67 | D68: =折现数据源!D67 | E68: =SUMPRODUCT(折现数据源!E$4:E$67,折现数据源!$D$4:$D$67)+SUMPRODUCT(折现数据源!F$4:F$67,折现数据源!$D$4:$D$67)+SUMPRODUCT(折现数据源!G$4:G$67,折现数据源!$D$4:$D$67)+SUMPRODUCT(折现数据源!H$4:H$67,折现数据源!$D$4:$D$67)+SUMPRODUCT(折现数据源!I$4:I$67,折现数据源!$D$4:$D$67)+SUMPRODUCT(折现数据源!J$4:J$67,折现数据源!$D$4:$D$67)+SUMPRODUCT(折现数据源!K$4:K$67,折现数据源!$D$4:$D$67)+SUMPRODUCT(折现数据源!L$4:L$67,折现数据源!$D$4:$D$67)+SUMPRODUCT(折现数据源!M$4:M$67,折现数据源!$D$4:$D$67)+SUMPRODUCT(折现数据源!N$4:N$67,折现数据源!$D$4:$D$67)+SUMPRODUCT(折现数据源!O$4:O$67,折现数据源!$D$4:$D$67)+SUMPRODUCT(折现数据源!P$4:P$67,折现数据源!$D$4:$D$67)+SUMPRODUCT(折现数据源!Q$4:Q$67,折现数据源!$D$4:$D$67)+SUMPRODUCT(折现数据源!R$4:R$67,折现数据源!$D$4:$D$67)+SUMPRODUCT(折现数据源!S$4:S$67,折现数据源!$D$4:$D$67)+SUMPRODUCT(折现数据源!T$4:T$67,折现数据源!$D$4:$D$67) | F68: =SUMPRODUCT(折现数据源!U$4:U$67,折现数据源!$D$4:$D$67)+SUMPRODUCT(折现数据源!V$4:V$67,折现数据源!$D$4:$D$67)+SUMPRODUCT(折现数据源!W$4:W$67,折现数据源!$D$4:$D$67)+SUMPRODUCT(折现数据源!X$4:X$67,折现数据源!$D$4:$D$67)+SUMPRODUCT(折现数据源!Y$4:Y$67,折现数据源!$D$4:$D$67)+SUMPRODUCT(折现数据源!Z$4:Z$67,折现数据源!$D$4:$D$67)+SUMPRODUCT(折现数据源!AA$4:AA$67,折现数据源!$D$4:$D$67) | G68: =IF(SUM($E$5:$E$68)=0,0,E68/SUM($E$5:$E$68)) | H68: =H67+G68
A69: 合计 | E69: =SUM(E5:E68) | F69: =SUM(F5:F68) | G69: =SUM(G5:G68)
A71: 久期贡献拆解 (Σ t×PV / Σ PV)
A72: 资产加权平均年数 Σ(t×PV)/Σ(PV) | E72: =SUMPRODUCT(B5:B68,E5:E68)/SUM(E5:E68)
A73: 负债加权平均年数 Σ(t×PV)/Σ(PV) | E73: =SUMPRODUCT(B5:B68,F5:F68)/SUM(F5:F68)
A74: 久期缺口 (资产 - 负债) | E74: =SUMPRODUCT(B5:B68,E5:E68)/SUM(E5:E68)-SUMPRODUCT(B5:B68,F5:F68)/SUM(F5:F68)

Sheet 计算逻辑说明
A1: 麦考林久期计算逻辑说明
A3: 【一】基础概念
A4: 麦考林久期 | B4: 衡量现金流回到面值的时间 = Σ(t × PV_t) / Σ(PV_t), 单位: 年
A5: 修正久期 | B5: D_mod = D_mac / (1 + y_avg), 利率变动 1% 时价格变动的百分比
A6: 久期缺口 GAP | B6: GAP = 资产久期 DA - 负债久期 DL, 衡量资产负债期限错配
A7: 加权平均收益率 | B7: y_avg = Σ(r_t × PV_t) / Σ(PV_t), PV 加权
A9: 【二】核心公式
A10: 折现因子 | B10: DF_t = 1 / (1 + r_t/100)^t r_t = 对应期限国债收益率 (%), t = 期限 (年)
A11: 单账户久期 | B11: D_i = Σ(t × PV_t) / Σ(PV_t) 其中 PV_t = CF_t × DF_t
A12: 组合久期 (PV 加权) | B12: DA = Σ(D_i × PV_i) / Σ(PV_i) (i ∈ 资产) DL = Σ(D_i × PV_i) / Σ(PV_i) (i ∈ 负债)
A13: 久期缺口 | B13: GAP = DA - DL
A14: 修正久期 | B14: D_mod = D_mac / (1 + y_avg)
A15: NII 敏感度 | B15: ΔNII/NII ≈ -GAP × Δr GAP > 0 (正缺口): 利率上行 → NII 受损
A17: 【三】Sheet 结构与公式联动
A18: 折现数据源 | B18: 🟢 C 列 (收益率) + E 列起 (现金流) = 可编辑输入区 🟣 D 列 (折现因子) = 公式 = 1/(1+C/100)^B → 修改输入, D 列自动重算
A19: 麦考林久期计算表 | B19: E 列 PV = SUMPRODUCT(现金流列, 折现因子列) F 列 Σt×PV = SUMPRODUCT(现金流列, 折现因子列, 年数列) G 列 D_mac = F/E H 列 D_mod = G/(1+I) 汇总用 SUMIF 按大类加权聚合
A20: 久期缺口与敏感性 | B20: C/D 列引用「麦考林久期计算表」汇总行 解读区用 IF/TEXT 函数自动生成文字结论
A21: 期限分布分析 | B21: 按期限汇总 Σ 各账户 CF × DF 底部用 SUMPRODUCT(B,E)/SUM(E) 独立复核久期 (交叉校验)
A23: 【四】数据基础
A24: 来源文件 | B24: prcp_basic_20251231_v5.xlsx → 基础数据 sheet
A25: 账户范围 | B25: 24 个末级账户 (is_leaf=1), 剔除汇总行避免重复计算
A26: 现金流列 | B26: C76-C139 = 剩余·1M-60M (60 段) + 剩余·10Y/15Y/20Y/30Y (4 段)
A27: 收益率曲线 | B27: B48-B111 = 64 段国债收益率 (中债登 2025-12-31 + 线性插值)
A28: 单位 | B28: 利率 = %, 现金流 = 亿元, 久期 = 年
A30: 【五】注意事项
A31: 适用性 | B31: 麦考林久期假设现金流一次性到期, 对分期偿还的贷款/存款存在偏差 生产环境建议用修正久期或利率敏感性 GAP (按重定价期限) 而非到期期限
A32: 行为假设 | B32: 活期存款未做「内核假设」处理, 若按 5 年最长期限重定价, 负债久期会显著上升 这是当前负债久期仅 0.32 年的主要原因
A33: 监管口径 | B33: 银保监《商业银行银行账户利率风险计量》要求以重定价期限 (repricing) 为核心, 麦考林久期可作为 EVE 分析的补充视角
A34: 重算提示 | B34: WPS/Excel 打开后如数值未更新, 按 Ctrl+Alt+F9 强制全表重算
